<?xml version = '1.0' encoding = 'UTF-8'?>
<Diagram class="oracle.dbtools.crest.swingui.relational.DPVRelational" name="Relational_1" id="89B3B81D-04E2-FE40-DCDC-D224AE6D6FB2">
<createdBy>windows</createdBy>
<createdTime>2013-11-09 05:53:12 UTC</createdTime>
<autoRoute>false</autoRoute>
<boxInbox>true</boxInbox>
<showLegend>false</showLegend>
<showLabels>false</showLabels>
<showRelAttributes>false</showRelAttributes>
<showGrid>false</showGrid>
<diagramColor>-1</diagramColor>
<display>false</display>
<notation>1</notation>
<objectViews>
<OView class="oracle.dbtools.crest.swingui.relational.TVTable" oid="09EC7AD8-A275-34CA-F5B4-3B340A7F77D7" otype="Table" vid="0E1D9FAF-3780-FDE5-3275-5AE7058AEEC1">
<hideElementsInCurrentOnly>false</hideElementsInCurrentOnly>
<bounds x="0" y="490" width="211" height="161"/>
</OView>
<OView class="oracle.dbtools.crest.swingui.relational.TVTable" oid="0E465438-3F5B-B963-480A-41D48C3AF7C8" otype="Table" vid="CF8893DE-94F7-4916-ECA3-38BC785CE192">
<hideElementsInCurrentOnly>false</hideElementsInCurrentOnly>
<bounds x="0" y="150" width="241" height="151"/>
</OView>
<OView class="oracle.dbtools.crest.swingui.relational.TVTable" oid="1B0C37BF-D3FF-A16F-1886-DFD4D0BFE2C2" otype="Table" vid="39445F9B-074E-B994-07AA-C0A0ECC70266">
<hideElementsInCurrentOnly>false</hideElementsInCurrentOnly>
<bounds x="1060" y="0" width="193" height="90"/>
</OView>
<OView class="oracle.dbtools.crest.swingui.relational.TVTable" oid="256A18A5-6E49-0919-3A46-7896A9D0EF89" otype="Table" vid="AE87D840-EE18-BC55-64A1-0261E2F94DEA">
<hideElementsInCurrentOnly>false</hideElementsInCurrentOnly>
<bounds x="290" y="580" width="242" height="141"/>
</OView>
<OView class="oracle.dbtools.crest.swingui.relational.TVTable" oid="4B794100-7294-90D5-5CEF-039A52995ED4" otype="Table" vid="647BEE27-B5A3-E663-222E-7A920D79394E">
<hideElementsInCurrentOnly>false</hideElementsInCurrentOnly>
<bounds x="1220" y="280" width="242" height="110"/>
</OView>
<OView class="oracle.dbtools.crest.swingui.relational.TVTable" oid="5560CB9A-FACA-D17A-EAB1-3377BA4B9C4D" otype="Table" vid="09843BFF-A91C-260B-B5CA-E6193B4BC4D4">
<hideElementsInCurrentOnly>false</hideElementsInCurrentOnly>
<bounds x="290" y="160" width="241" height="110"/>
</OView>
<OView class="oracle.dbtools.crest.swingui.relational.TVTable" oid="5DF50448-3999-0041-C897-2718F90A9CE6" otype="Table" vid="7B014F2A-8DA7-6F18-521F-B61801E155C4">
<hideElementsInCurrentOnly>false</hideElementsInCurrentOnly>
<bounds x="1220" y="630" width="240" height="110"/>
</OView>
<OView class="oracle.dbtools.crest.swingui.relational.TVTable" oid="86084C88-350B-2C3B-AEB4-47E682599CF0" otype="Table" vid="CBAB1FBE-6A5F-2937-E579-A3821491C021">
<hideElementsInCurrentOnly>false</hideElementsInCurrentOnly>
<bounds x="280" y="0" width="251" height="132"/>
</OView>
<OView class="oracle.dbtools.crest.swingui.relational.TVTable" oid="87AD444B-E8F1-F361-0EBF-3998659276F8" otype="Table" vid="E43EC69D-993E-88D9-FEF7-867F17400AA4">
<hideElementsInCurrentOnly>false</hideElementsInCurrentOnly>
<bounds x="610" y="0" width="170" height="121"/>
</OView>
<OView class="oracle.dbtools.crest.swingui.relational.TVTable" oid="9B065EB4-F52C-5E83-9382-6A7BA00028B9" otype="Table" vid="AFBA6392-9C9B-387E-A1C8-9E23EDBCDE6F">
<hideElementsInCurrentOnly>false</hideElementsInCurrentOnly>
<bounds x="0" y="680" width="211" height="130"/>
</OView>
<OView class="oracle.dbtools.crest.swingui.relational.TVTable" oid="A234597D-CE38-BF2A-13D3-A3DFEAE3039A" otype="Table" vid="B1DC682D-CEF7-0815-B838-897309114DE5">
<hideElementsInCurrentOnly>false</hideElementsInCurrentOnly>
<bounds x="580" y="340" width="231" height="202"/>
</OView>
<OView class="oracle.dbtools.crest.swingui.relational.TVTable" oid="A80ADC34-7B35-4C03-C335-7FE1B28E887D" otype="Table" vid="404B2B57-433D-9B6D-716E-222819DB5617">
<hideElementsInCurrentOnly>false</hideElementsInCurrentOnly>
<bounds x="0" y="370" width="191" height="110"/>
</OView>
<OView class="oracle.dbtools.crest.swingui.relational.TVTable" oid="BC6A9FC5-BC25-B96F-0BA4-EFCEA365C0F6" otype="Table" vid="3F9BF99D-C3AD-83C2-42D5-BB161CF392B8">
<hideElementsInCurrentOnly>false</hideElementsInCurrentOnly>
<bounds x="290" y="340" width="241" height="181"/>
</OView>
<OView class="oracle.dbtools.crest.swingui.relational.TVTable" oid="C0867DCE-6241-9FF6-7B3D-157CBAC8048E" otype="Table" vid="C914A7B4-A456-7E58-9621-E56702EC4AE1">
<hideElementsInCurrentOnly>false</hideElementsInCurrentOnly>
<bounds x="1220" y="450" width="240" height="110"/>
</OView>
<OView class="oracle.dbtools.crest.swingui.relational.TVTable" oid="C9A4E057-0A22-9B61-B773-35463C351AB0" otype="Table" vid="464DF0DD-D342-29A5-ACE0-0F5C5966E9A2">
<hideElementsInCurrentOnly>false</hideElementsInCurrentOnly>
<bounds x="610" y="140" width="170" height="120"/>
</OView>
<OView class="oracle.dbtools.crest.swingui.relational.TVTable" oid="EF256ECE-B2D4-E85C-9642-080070E4B4A3" otype="Table" vid="64518798-94AB-F572-1961-214FFC154010">
<hideElementsInCurrentOnly>false</hideElementsInCurrentOnly>
<bounds x="580" y="580" width="231" height="110"/>
</OView>
<OView class="oracle.dbtools.crest.swingui.relational.TVTable" oid="F41E950F-9997-18C8-E38A-14C39A28AEC2" otype="Table" vid="6B4CEAA2-8C8B-2CEE-E89D-A1A9604FCBB0">
<hideElementsInCurrentOnly>false</hideElementsInCurrentOnly>
<bounds x="1220" y="120" width="242" height="111"/>
</OView>
<OView class="oracle.dbtools.crest.swingui.relational.TVTable" oid="F47F912E-CF01-F800-50FA-CAAA7B4D2D63" otype="Table" vid="B80FA190-365D-7D66-E2F8-0039DE6A5858">
<hideElementsInCurrentOnly>false</hideElementsInCurrentOnly>
<bounds x="960" y="140" width="199" height="105"/>
</OView>
<OView class="oracle.dbtools.crest.swingui.relational.TVTable" oid="F697DB53-413F-6C7F-9C1B-707A5ED9CB8E" otype="Table" vid="8E786709-E43A-8A19-4968-71E4E301B912">
<hideElementsInCurrentOnly>false</hideElementsInCurrentOnly>
<bounds x="820" y="0" width="199" height="90"/>
</OView>
</objectViews>
<connectors>
<Connector class="oracle.dbtools.crest.swingui.relational.TVFKRelation" oid="106E5CC7-A5F3-A3AF-6904-94EE6030159F" otype="FKIndexAssociation" vid_source="8E786709-E43A-8A19-4968-71E4E301B912" vid_target="B80FA190-365D-7D66-E2F8-0039DE6A5858">
<hideElementsInCurrentOnly>false</hideElementsInCurrentOnly>
<lineWidth>1</lineWidth>
<points>
<point x="989" y="90"/>
<point x="989" y="140"/>
</points>
</Connector>
<Connector class="oracle.dbtools.crest.swingui.relational.TVFKRelation" oid="17D130C1-F619-65A2-83AD-54A5F428A275" otype="FKIndexAssociation" vid_source="AE87D840-EE18-BC55-64A1-0261E2F94DEA" vid_target="3F9BF99D-C3AD-83C2-42D5-BB161CF392B8">
<hideElementsInCurrentOnly>false</hideElementsInCurrentOnly>
<lineWidth>1</lineWidth>
<points>
<point x="410" y="580"/>
<point x="410" y="521"/>
</points>
</Connector>
<Connector class="oracle.dbtools.crest.swingui.relational.TVFKRelation" oid="28474AED-B1BA-2D2E-4F7D-22420B70BE41" otype="FKIndexAssociation" vid_source="3F9BF99D-C3AD-83C2-42D5-BB161CF392B8" vid_target="404B2B57-433D-9B6D-716E-222819DB5617">
<hideElementsInCurrentOnly>false</hideElementsInCurrentOnly>
<lineWidth>1</lineWidth>
<points>
<point x="290" y="425"/>
<point x="191" y="425"/>
</points>
</Connector>
<Connector class="oracle.dbtools.crest.swingui.relational.TVFKRelation" oid="2E0507B8-B418-6B18-F2AE-AD3D206616DE" otype="FKIndexAssociation" vid_source="CF8893DE-94F7-4916-ECA3-38BC785CE192" vid_target="09843BFF-A91C-260B-B5CA-E6193B4BC4D4">
<hideElementsInCurrentOnly>false</hideElementsInCurrentOnly>
<lineWidth>1</lineWidth>
<points>
<point x="241" y="215"/>
<point x="290" y="215"/>
</points>
</Connector>
<Connector class="oracle.dbtools.crest.swingui.relational.TVFKRelation" oid="3E63C9AA-2D3B-FC1C-E8B3-36DD9729DB49" otype="FKIndexAssociation" vid_source="647BEE27-B5A3-E663-222E-7A920D79394E" vid_target="6B4CEAA2-8C8B-2CEE-E89D-A1A9604FCBB0">
<hideElementsInCurrentOnly>false</hideElementsInCurrentOnly>
<lineWidth>1</lineWidth>
<points>
<point x="1341" y="280"/>
<point x="1341" y="231"/>
</points>
</Connector>
<Connector class="oracle.dbtools.crest.swingui.relational.TVFKRelation" oid="4503C381-437B-A5C5-73CC-1BB1508115BC" otype="FKIndexAssociation" vid_source="B80FA190-365D-7D66-E2F8-0039DE6A5858" vid_target="CBAB1FBE-6A5F-2937-E579-A3821491C021">
<hideElementsInCurrentOnly>false</hideElementsInCurrentOnly>
<lineWidth>1</lineWidth>
<points>
<point x="960" y="170"/>
<point x="901" y="170"/>
<point x="901" y="129"/>
<point x="531" y="129"/>
</points>
</Connector>
<Connector class="oracle.dbtools.crest.swingui.relational.TVFKRelation" oid="4F8ECF41-DB44-9132-5A80-EB5A760BF8C7" otype="FKIndexAssociation" vid_source="CBAB1FBE-6A5F-2937-E579-A3821491C021" vid_target="CF8893DE-94F7-4916-ECA3-38BC785CE192">
<hideElementsInCurrentOnly>false</hideElementsInCurrentOnly>
<lineWidth>1</lineWidth>
<points>
<point x="280" y="60"/>
<point x="130" y="60"/>
<point x="130" y="150"/>
</points>
</Connector>
<Connector class="oracle.dbtools.crest.swingui.relational.TVFKRelation" oid="69DA3EE9-390E-FA55-46DA-12646953D10B" otype="FKIndexAssociation" vid_source="AE87D840-EE18-BC55-64A1-0261E2F94DEA" vid_target="AFBA6392-9C9B-387E-A1C8-9E23EDBCDE6F">
<hideElementsInCurrentOnly>false</hideElementsInCurrentOnly>
<lineWidth>1</lineWidth>
<points>
<point x="290" y="700"/>
<point x="211" y="700"/>
</points>
</Connector>
<Connector class="oracle.dbtools.crest.swingui.relational.TVFKRelation" oid="7950D1AC-FBF9-8A9D-F816-78E0AA974AA9" otype="FKIndexAssociation" vid_source="CBAB1FBE-6A5F-2937-E579-A3821491C021" vid_target="464DF0DD-D342-29A5-ACE0-0F5C5966E9A2">
<hideElementsInCurrentOnly>false</hideElementsInCurrentOnly>
<lineWidth>1</lineWidth>
<points>
<point x="531" y="70"/>
<point x="569" y="70"/>
<point x="569" y="200"/>
<point x="610" y="200"/>
</points>
</Connector>
<Connector class="oracle.dbtools.crest.swingui.relational.TVFKRelation" oid="8F81CA89-95AB-E3F9-0F4F-F256012F8698" otype="FKIndexAssociation" vid_source="CBAB1FBE-6A5F-2937-E579-A3821491C021" vid_target="E43EC69D-993E-88D9-FEF7-867F17400AA4">
<hideElementsInCurrentOnly>false</hideElementsInCurrentOnly>
<lineWidth>1</lineWidth>
<points>
<point x="531" y="80"/>
<point x="610" y="80"/>
</points>
</Connector>
<Connector class="oracle.dbtools.crest.swingui.relational.TVFKRelation" oid="99577288-0811-2E27-A663-044AC740443E" otype="FKIndexAssociation" vid_source="8E786709-E43A-8A19-4968-71E4E301B912" vid_target="39445F9B-074E-B994-07AA-C0A0ECC70266">
<hideElementsInCurrentOnly>false</hideElementsInCurrentOnly>
<lineWidth>1</lineWidth>
<points>
<point x="1019" y="45"/>
<point x="1060" y="45"/>
</points>
</Connector>
<Connector class="oracle.dbtools.crest.swingui.relational.TVFKRelation" oid="B85B05C5-1264-D0E6-9896-64D794D5EFA0" otype="FKIndexAssociation" vid_source="B80FA190-365D-7D66-E2F8-0039DE6A5858" vid_target="B1DC682D-CEF7-0815-B838-897309114DE5">
<hideElementsInCurrentOnly>false</hideElementsInCurrentOnly>
<lineWidth>1</lineWidth>
<points>
<point x="1021" y="245"/>
<point x="1021" y="391"/>
<point x="811" y="391"/>
</points>
</Connector>
<Connector class="oracle.dbtools.crest.swingui.relational.TVFKRelation" oid="BE0926BD-C2DA-7699-5C3E-628C83FBDF11" otype="FKIndexAssociation" vid_source="647BEE27-B5A3-E663-222E-7A920D79394E" vid_target="C914A7B4-A456-7E58-9621-E56702EC4AE1">
<hideElementsInCurrentOnly>false</hideElementsInCurrentOnly>
<lineWidth>1</lineWidth>
<points>
<point x="1340" y="390"/>
<point x="1340" y="450"/>
</points>
</Connector>
<Connector class="oracle.dbtools.crest.swingui.relational.TVFKRelation" oid="C1DCC2E1-F9B4-37A3-31C0-4BCD558A5D16" otype="FKIndexAssociation" vid_source="3F9BF99D-C3AD-83C2-42D5-BB161CF392B8" vid_target="CF8893DE-94F7-4916-ECA3-38BC785CE192">
<hideElementsInCurrentOnly>false</hideElementsInCurrentOnly>
<lineWidth>1</lineWidth>
<points>
<point x="290" y="359"/>
<point x="130" y="359"/>
<point x="130" y="301"/>
</points>
</Connector>
<Connector class="oracle.dbtools.crest.swingui.relational.TVFKRelation" oid="D427D64F-B7F1-4229-5F24-5F5E57CD22EE" otype="FKIndexAssociation" vid_source="7B014F2A-8DA7-6F18-521F-B61801E155C4" vid_target="C914A7B4-A456-7E58-9621-E56702EC4AE1">
<hideElementsInCurrentOnly>false</hideElementsInCurrentOnly>
<lineWidth>1</lineWidth>
<points>
<point x="1340" y="630"/>
<point x="1340" y="560"/>
</points>
</Connector>
<Connector class="oracle.dbtools.crest.swingui.relational.TVFKRelation" oid="D81542A7-9FFE-29F1-CDCD-908F035099B7" otype="FKIndexAssociation" vid_source="B80FA190-365D-7D66-E2F8-0039DE6A5858" vid_target="AE87D840-EE18-BC55-64A1-0261E2F94DEA">
<hideElementsInCurrentOnly>false</hideElementsInCurrentOnly>
<lineWidth>1</lineWidth>
<points>
<point x="1150" y="245"/>
<point x="1150" y="760"/>
<point x="411" y="760"/>
<point x="411" y="721"/>
</points>
</Connector>
<Connector class="oracle.dbtools.crest.swingui.relational.TVFKRelation" oid="DF88F539-4E42-7D1C-DD86-92E22C64152F" otype="FKIndexAssociation" vid_source="39445F9B-074E-B994-07AA-C0A0ECC70266" vid_target="B80FA190-365D-7D66-E2F8-0039DE6A5858">
<hideElementsInCurrentOnly>false</hideElementsInCurrentOnly>
<lineWidth>1</lineWidth>
<points>
<point x="1119" y="90"/>
<point x="1119" y="140"/>
</points>
</Connector>
<Connector class="oracle.dbtools.crest.swingui.relational.TVFKRelation" oid="E3EA7FAA-506D-01A9-A44F-07EDDEBB26DD" otype="FKIndexAssociation" vid_source="B80FA190-365D-7D66-E2F8-0039DE6A5858" vid_target="3F9BF99D-C3AD-83C2-42D5-BB161CF392B8">
<hideElementsInCurrentOnly>false</hideElementsInCurrentOnly>
<lineWidth>1</lineWidth>
<points>
<point x="960" y="229"/>
<point x="790" y="229"/>
<point x="790" y="320"/>
<point x="410" y="320"/>
<point x="410" y="340"/>
</points>
</Connector>
<Connector class="oracle.dbtools.crest.swingui.relational.TVFKRelation" oid="E74A4651-7731-7CD6-8092-2C6BC6BF4415" otype="FKIndexAssociation" vid_source="AE87D840-EE18-BC55-64A1-0261E2F94DEA" vid_target="0E1D9FAF-3780-FDE5-3275-5AE7058AEEC1">
<hideElementsInCurrentOnly>false</hideElementsInCurrentOnly>
<lineWidth>1</lineWidth>
<points>
<point x="290" y="615"/>
<point x="211" y="615"/>
</points>
</Connector>
<Connector class="oracle.dbtools.crest.swingui.relational.TVFKRelation" oid="EF0897D7-BF29-5976-0AB9-13B0EC910F24" otype="FKIndexAssociation" vid_source="B1DC682D-CEF7-0815-B838-897309114DE5" vid_target="64518798-94AB-F572-1961-214FFC154010">
<hideElementsInCurrentOnly>false</hideElementsInCurrentOnly>
<lineWidth>1</lineWidth>
<points>
<point x="695" y="542"/>
<point x="695" y="580"/>
</points>
</Connector>
</connectors>
<arcs>
<Arc class="oracle.dbtools.crest.swingui.relational.TVFKArc" oid="4E588985-5375-6EDD-5A75-D23EF7F379D1" otype="FKArc" vid="1A9E9E88-FA45-B78B-6274-54D75AECF6ED">
<hideElementsInCurrentOnly>false</hideElementsInCurrentOnly>
<bounds x="260" y="-20" width="291" height="172"/>
</Arc>
<Arc class="oracle.dbtools.crest.swingui.relational.TVFKArc" oid="B35F507B-297E-4162-3F0C-2125F5706400" otype="FKArc" vid="8B4CE589-8D35-DE89-70FB-22B8E94BCCB1">
<hideElementsInCurrentOnly>false</hideElementsInCurrentOnly>
<bounds x="270" y="560" width="282" height="181"/>
</Arc>
</arcs>
</Diagram>